simple_json_utils/__init__.py
simple_json_utils/simple_json_utils.py
simple_json_utils-0.0.2.dist-info/METADATA
simple_json_utils-0.0.2.dist-info/WHEEL
simple_json_utils-0.0.2.dist-info/RECORD
