Metadata-Version: 2.1
Name: simple_json_utils
Version: 0.0.2
Summary: A simple json utilities package
Project-URL: Homepage, https://github.com/Tr4nt420/simple_json_utils
Author-email: Tr4nt <trantando69@gmail.com>
Classifier: License :: OSI Approved :: MIT License
Classifier: Operating System :: OS Independent
Classifier: Programming Language :: Python :: 3
Requires-Python: >=3.7
